[{"s": "2612-kartridzh-na-kakoj-printer", "t": "Картридж 2612: совместимость с принтерами HP, Canon, Xerox", "i": "📁", "c": null}, {"s": "26x-kartridzh-dlya-kakogo-printera", "t": "26X картридж: совместимость с принтерами HP, Canon и другими", "i": "📦", "c": "raskhodnye-materialy"}, {"s": "2612a-kartridzh-kakoj-printer", "t": "2612A картридж: совместимые принтеры HP и аналоги 2026", "i": "📁", "c": null}, {"s": "2612-dlya-kakogo-printera", "t": "Картридж 2612: для каких принтеров подходит и как выбрать аналог", "i": "📦", "c": "raskhodnye-materialy"}, {"s": "2612a-kartridzh-dlya-kakikh-printerov", "t": "Картридж 2612а: совместимость с принтерами HP, Canon, Samsung и Xerox", "i": "📁", "c": null}, {"s": "2612a-kartridzh-ot-kakogo-printera", "t": "Картридж 2612a: от каких принтеров подходит и что это", "i": "📁", "c": null}, {"s": "26x-kartridzh-kakoj-printer", "t": "Какие принтеры HP используют картридж 26x: полный список моделей", "i": "📁", "c": null}, {"s": "2612a-kartridzh-dlya-kakogo-printera", "t": "Картридж 2612A: список совместимых принтеров и расходники", "i": "📁", "c": null}, {"s": "2612a-kartridzh-dlya-kakikh-printerov-canon", "t": "2612A картридж: список принтеров Canon, совместимость и выбор", "i": "📁", "c": null}, {"s": "26x-kartridzh-k-kakomu-printeru", "t": "26x картридж к какому принтеру: список моделей и совместимость", "i": "📁", "c": null}, {"s": "2612a-kakoj-printer", "t": "Принтер штрих-кода 2612А: обзор, драйверы и настройка", "i": "📁", "c": null}, {"s": "2612-kakoj-printer", "t": "Принтер 2612: какой это модель, характеристики и драйверы", "i": "📁", "c": null}, {"s": "2613-kartridzh-dlya-kakikh-printerov", "t": "2613 картридж для каких принтеров: полная совместимость и выбор", "i": "📁", "c": null}, {"s": "2612a-kartridzh-dlya-kakikh-printerov-hp", "t": "HP 2612A картридж: список совместимых принтеров и характеристики", "i": "📁", "c": null}]