[{"s": "d111s-dlya-kakikh-printerov", "t": "Картриджи D111S: совместимость с принтерами HP, Canon, Brother", "i": "📦", "c": "raskhodnye-materialy"}, {"s": "d117s-kartridzh-dlya-kakogo-printera", "t": "D117S картридж для какого принтера: полная совместимость и аналоги", "i": "📁", "c": null}, {"s": "d104s-dlya-kakikh-printerov", "t": "D104S для каких принтеров: полная совместимость и установка", "i": "📁", "c": null}, {"s": "d111s-kartridzh-dlya-kakogo-printera", "t": "D111S картридж: для каких принтеров подходит, замена и совместимость", "i": "📁", "c": null}, {"s": "d105l-kartridzh-dlya-kakogo-printera", "t": "D105L картридж: для какого принтера подойдет? Полная совместимость", "i": "📁", "c": null}, {"s": "d119s-kartridzh-dlya-kakogo-printera", "t": "Картридж D119S: для каких принтеров подходит и как выбрать", "i": "📁", "c": null}, {"s": "d101s-kartridzh-kakoj-printer", "t": "D101S картридж: для каких принтеров подходит и совместимость", "i": "📁", "c": null}, {"s": "d115l-kartridzh-na-kakoj-printer", "t": "Картридж D115L: на какие принтеры подходит и где купить", "i": "📁", "c": null}, {"s": "d111s-na-kakie-printery-podkhodit", "t": "Совместимость термоленты D111S: для каких принтеров подходит", "i": "📁", "c": null}, {"s": "d104s-kakoj-printer", "t": "Принтер D104S: обзор, характеристики и инструкция по настройке", "i": "📁", "c": null}, {"s": "d105s-kartridzh-dlya-kakikh-printerov", "t": "D105S картридж: для каких принтеров, совместимость и замена", "i": "📁", "c": null}, {"s": "d104s-kartridzh-dlya-kakikh-printerov", "t": "Картридж D104S: какие принтеры поддерживают, аналоги и совместимость", "i": "📁", "c": null}, {"s": "d101s-kartridzh-dlya-kakikh-printerov", "t": "D101S картридж: для каких принтеров, совместимость и аналоги", "i": "📁", "c": null}, {"s": "d101s-kartridzh-dlya-kakikh-printerov-podkhodit", "t": "D101S картридж: совместимость с принтерами и классификация типов этикеток", "i": "📁", "c": null}, {"s": "d109s-dlya-kakogo-printera", "t": "D109S для какого принтера: Совместимость и замена этикеток", "i": "📁", "c": null}]