[{"s": "initsializatsiya-na-printere-chto-eto", "t": "Инициализация принтера — что это такое и как её выполнить", "i": "📁", "c": null}, {"s": "instruktsiya-kak-podklyuchit-printer-k-noutbuku", "t": "Как подключить принтер к ноутбуку: пошаговая инструкция 2026", "i": "📁", "c": null}, {"s": "informatika-chto-takoe-printer", "t": "Принтер — что это такое в информатике: устройство, виды и применение", "i": "📁", "c": null}, {"s": "instruktsiya-kak-raspechatat-s-telefona-na-printer", "t": "Как распечатать с телефона на принтер: пошаговая инструкция 2026", "i": "📁", "c": null}, {"s": "instaks-printer-kak-polzovatsya", "t": "Instax принтер: как пользоваться — пошаговая инструкция 2026", "i": "📁", "c": null}, {"s": "instruktsiya-kak-raspechatat-s-printera", "t": "Как распечатать документ с принтера: пошаговая инструкция 2026", "i": "📁", "c": null}, {"s": "instruktsiya-kak-pechatat-na-printere", "t": "Как печатать на принтере: пошаговая инструкция для новичков", "i": "📁", "c": null}, {"s": "instruktsiyu-kak-polzovatsya-printerom", "t": "Как пользоваться принтером: пошаговая инструкция для новичков", "i": "📁", "c": null}, {"s": "initsializatsiya-na-printere-chto-delat", "t": "Ошибка инициализации принтера: причины, методы устранения и сброс", "i": "🛠️", "c": "remont-i-oshibki"}, {"s": "instruktsiya-kak-ispolzovat-printer", "t": "Как использовать принтер: Полная инструкция по настройке и печати", "i": "📁", "c": null}, {"s": "instruktsiya-kak-skanirovat-s-printera-na-kompyuter", "t": "Как сканировать с принтера на компьютер: полные инструкции 2026", "i": "📁", "c": null}, {"s": "instruktsiya-kak-polzovatsya-mini-printerom", "t": "Полная инструкция: как пользоваться мини-принтером и настраивать его", "i": "📁", "c": null}, {"s": "instruktsiya-kak-polzovatsya-printerom-hp", "t": "Как пользоваться принтером HP: Полная инструкция по настройке и печати", "i": "📁", "c": null}, {"s": "incorrect-port-canon-lbp-2900-chto-delat", "t": "Ошибка incorrect port Canon LBP 2900: полное руководство по исправлению", "i": "📁", "c": null}, {"s": "inf-fajl-printera-gde-nakhoditsya", "t": "Где найти и как открыть INF-файл драйвера принтера: Полный гайд", "i": "📁", "c": null}, {"s": "interernye-printery-na-chem-pechatayut", "t": "На чем печатают интерьерные принтеры: материалы и основы", "i": "📁", "c": null}, {"s": "incompatible-printer-canon-chto-delat", "t": "Ошибка incompatible printer Canon: причины и способы решения", "i": "🛠️", "c": "remont-i-oshibki"}, {"s": "instruktsiya-kak-raspechatat-dokument-na-printere-s-kompyutera", "t": "Как распечатать документ с компьютера: инструкция для Windows и Mac", "i": "📁", "c": null}, {"s": "instruktsiya-kak-sbrosit-schetchik-na-printere-brother", "t": "Как сбросить счетчик тонера и фотобарабана на принтерах Brother", "i": "🛠️", "c": "remont-i-oshibki"}, {"s": "installation-has-been-interrupted-canon-chto-delat", "t": "Ошибка installation has been interrupted Canon: полное решение", "i": "📁", "c": null}, {"s": "instruktsiya-kak-skanirovat-dokument-s-printera-na-kompyuter", "t": "Как сканировать документ с принтера на компьютер: Полная инструкция", "i": "📁", "c": null}, {"s": "interfejsnyj-usb-kabel-dlya-printera-chto-eto", "t": "Интерфейсный USB кабель для принтера: что это и как выбрать", "i": "📁", "c": null}, {"s": "instruktsiya-kak-polzovatsya-printerom-canon-pixma", "t": "Как пользоваться принтером Canon Pixma: Полная инструкция по настройке и печати", "i": "📁", "c": null}, {"s": "indikator-tonera-na-printere-chto-eto", "t": "Индикатор тонера на принтере: что означают значки и как устранить ошибку", "i": "📦", "c": "raskhodnye-materialy"}, {"s": "initsializatsiya-printera-chto-eto", "t": "Инициализация принтера: что это, зачем нужна и как выполнить сброс", "i": "📁", "c": null}, {"s": "initsializatsiya-printera-chto-delat", "t": "Инициализация принтера: как сбросить настройки и настроить устройство", "i": "📁", "c": null}, {"s": "instruktsiya-kak-pravilno-ustanovit-printer", "t": "Как правильно установить принтер: полная инструкция по подключению", "i": "📁", "c": null}, {"s": "instruktsiya-kak-sdelat-kserokopiyu-na-printere", "t": "Как сделать ксерокопию на принтере: пошаговая инструкция и советы", "i": "📁", "c": null}]