[{"s": "iz-za-chego-mozhet-printer", "t": "Почему не работает принтер: 12 причин и способы устранения", "i": "🛠️", "c": "remont-i-oshibki"}, {"s": "iz-chego-pechataet-3-d-printer-iz-kakogo-materiala", "t": "Из чего печатает 3D-принтер? Материалы для 3D-печати в 2026 году", "i": "📁", "c": null}, {"s": "izdeliya-iz-3d-printera-chto-mozhno-sdelat", "t": "Что можно сделать на 3D-принтере: 50 идей для дома и бизнеса", "i": "📁", "c": null}, {"s": "iznoshen-baraban-na-printere-panasonik-chto-delat", "t": "Износ барабана принтера Panasonic: причины и ремонт", "i": "🛠️", "c": "remont-i-oshibki"}, {"s": "iz-chego-pechatayut-organy-na-3d-printere", "t": "Из чего печатают органы на 3D-принтере: материалы и технологии 2026", "i": "📁", "c": null}, {"s": "iz-chego-sdelana-nit-dlya-3d-printera", "t": "Из чего делают нить для 3D-принтера: состав, виды и свойства", "i": "📁", "c": null}, {"s": "izolyatsiya-drajverov-printerov-ot-sluzhby-pechati-chto-eto", "t": "Изоляция драйверов принтеров от службы печати: что это и зачем нужно", "i": "📁", "c": null}, {"s": "iz-chego-sdelat-termokameru-dlya-3d-printera", "t": "Термокамера для 3D-принтера: материалы и инструкция по сборке", "i": "📁", "c": null}, {"s": "iz-chego-mozhno-sdelat-krasku-dlya-printera", "t": "Как сделать краску для принтера своими руками: 7 проверенных рецептов", "i": "📁", "c": null}, {"s": "iz-za-chego-kompyuter-ne-vidit-printer", "t": "Компьютер не видит принтер: причины и решения (2026)", "i": "📁", "c": null}, {"s": "iz-za-chego-mazhet-lazernyj-printer", "t": "Почему мажет лазерный принтер: 10 причин и как устранить", "i": "📁", "c": null}, {"s": "iz-za-chego-mozhet-slomatsya-printer", "t": "Почему ломается принтер: 12 причин и способы устранения", "i": "🛠️", "c": "remont-i-oshibki"}, {"s": "iz-za-chego-ne-vklyuchaetsya-printer", "t": "Принтер не включается: 12 причин и способы ремонта (2026)", "i": "📁", "c": null}, {"s": "iz-chego-3d-printer-delaet-veshchi", "t": "Из чего 3D-принтер делает вещи: материалы и их особенности", "i": "📁", "c": null}, {"s": "iz-chego-sdelan-kartridzh-dlya-printera", "t": "Из чего сделан картридж для принтера: состав, материалы и особенности", "i": "📦", "c": "raskhodnye-materialy"}, {"s": "iz-chego-delayut-bumagu-dlya-printera", "t": "Из чего делают бумагу для принтера: состав, виды и особенности", "i": "📦", "c": "raskhodnye-materialy"}, {"s": "iz-chego-delayut-pampersy-dlya-printera", "t": "Из чего делают памперсы для принтера: состав и особенности", "i": "📁", "c": null}, {"s": "iz-chego-sdelan-printer", "t": "Из чего сделан принтер: материалы и технологии производства", "i": "📁", "c": "drugoe"}, {"s": "iz-chego-sdelat-stol-dlya-3d-printera", "t": "Стол для 3D-принтера: 10 лучших материалов и конструкций", "i": "📁", "c": null}, {"s": "iz-za-chego-printer-pechataet-polosami", "t": "Принтер печатает полосами: 12 причин и как исправить самостоятельно", "i": "🛠️", "c": "remont-i-oshibki"}, {"s": "iz-chego-pechataet-3d-printer-doma", "t": "Из чего печатает 3D принтер дома: виды материалов и филаментов", "i": "📁", "c": null}, {"s": "iz-printera-vytekaet-kraska-chto-delat", "t": "Принтер течет краской: причины, экстренная помощь и ремонт", "i": "🛠️", "c": "remont-i-oshibki"}, {"s": "iz-za-chego-dymit-printer", "t": "Почему дымит принтер: причины, диагностика и безопасное решение", "i": "🛠️", "c": "remont-i-oshibki"}, {"s": "iz-chego-delayut-printer", "t": "Внутреннее устройство принтера: Из каких материалов и деталей он сделан", "i": "📁", "c": null}, {"s": "iz-chego-kraska-dlya-printera", "t": "Состав чернил для струйных принтеров: из чего делают краски", "i": "📁", "c": null}, {"s": "iz-kakogo-materiala-mozhno-pechatat-na-3d-printere", "t": "Материалы для 3D-печати: полный гид по пластикам и смолам", "i": "📁", "c": null}, {"s": "iz-chego-delayut-chernila-dlya-printera", "t": "Из чего делают чернила для принтера: состав, виды и особенности", "i": "📁", "c": null}, {"s": "iz-chego-sdelan-3d-printer", "t": "Из чего сделан 3D-принтер: устройство, материалы и компоненты", "i": "📁", "c": null}, {"s": "iznoshen-baraban-na-printere-chto-delat", "t": "Износ фотобарабана принтера: признаки, диагностика и замена", "i": "🛠️", "c": "remont-i-oshibki"}, {"s": "iz-chego-delayut-plastik-dlya-3d-printera", "t": "Из чего делают пластик для 3D принтера: состав, виды и свойства", "i": "📁", "c": null}, {"s": "iz-za-chego-printer-pechataet-s-polosami-kak-ispravit", "t": "Почему принтер печатает с полосами: причины и как исправить дефект", "i": "🛠️", "c": "remont-i-oshibki"}, {"s": "iz-chego-delayut-krasku-dlya-printerov", "t": "Состав чернил для принтеров: чем отличаются струйные и сублимационные?", "i": "📁", "c": null}, {"s": "iz-chego-pechatayut-na-3d-printere", "t": "Из чего печатают на 3д принтере: виды пластика и материала", "i": "📁", "c": null}, {"s": "iz-kakogo-materiala-delayut-printery", "t": "Из какого материала делают принтеры: обзор корпусов и компонентов", "i": "📁", "c": null}, {"s": "iz-kakogo-yazyka-slovo-printer", "t": "Этимология слова принтер: откуда к нам пришло название?", "i": "📁", "c": null}, {"s": "iz-za-chego-mozhet-printer-zazhevyvaet-bumagu", "t": "Принтер жует бумагу: 7 главных причин и способы ремонта", "i": "🛠️", "c": "remont-i-oshibki"}, {"s": "iz-chego-sdelan-poroshok-dlya-printera", "t": "Из чего сделан порошок для принтера: состав, компоненты и безопасность", "i": "📁", "c": null}, {"s": "iz-za-chego-mozhet-ne-rabotat-printer", "t": "Почему не работает принтер: основные причины и способы устранения", "i": "🛠️", "c": "remont-i-oshibki"}, {"s": "iz-chego-delayut-krasku-dlya-lazernogo-printera", "t": "Из чего делают тонер для лазерных принтеров: состав и свойства", "i": "🛠️", "c": "remont-i-oshibki"}, {"s": "iz-kakikh-materialov-sdelan-printer", "t": "Из каких материалов сделан принтер: полный разбор конструкции", "i": "📁", "c": null}, {"s": "iz-chego-proizvodyat-bumagu-dlya-printera", "t": "Из чего делают бумагу для принтера: состав, сырье и типы волокон", "i": "📁", "c": null}, {"s": "iz-chego-delaetsya-printer", "t": "Из чего состоит принтер: материалы, компоненты и устройство", "i": "📁", "c": null}, {"s": "iz-za-chego-mozhet-ne-pechat-printer", "t": "Почему не печатает принтер: основные причины и способы решения", "i": "🛠️", "c": "remont-i-oshibki"}, {"s": "iz-za-chego-printer-zazhevyvaet-bumagu", "t": "Принтер зажевывает бумагу: 7 главных причин и способы устранения", "i": "🛠️", "c": "remont-i-oshibki"}, {"s": "iz-chego-pechatayut-3d-printery", "t": "Материалы для 3D печати: полный обзор технологий и расходников", "i": "📁", "c": null}, {"s": "iz-kakikh-materialov-pechataet-3d-printer", "t": "Обзор материалов для 3D-печати: виды пластика и их свойства", "i": "📁", "c": null}, {"s": "iz-za-chego-printer-pechataet-polosami-strujnyj", "t": "Почему струйный принтер печатает полосами: 7 причин и решения", "i": "🛠️", "c": "remont-i-oshibki"}, {"s": "iz-chego-toner-dlya-printera", "t": "Из чего сделан тонер: состав, виды и влияние на печать", "i": "📁", "c": null}, {"s": "iz-za-chego-proiskhodit-zamyatie-bumagi-v-printere", "t": "Почему заминает бумагу в принтере: 7 главных причин и решения", "i": "📁", "c": null}, {"s": "iz-chego-sdelat-pampers-dlya-printera", "t": "Из чего сделать памперс для принтера: материалы и DIY-замена", "i": "🛠️", "c": "remont-i-oshibki"}, {"s": "iz-chego-delaetsya-kraska-dlya-printera", "t": "Из чего состоит краска для принтера: состав чернил и картриджей", "i": "📁", "c": null}, {"s": "iz-za-chego-ne-pechataet-printer-canon", "t": "Почему не печатает принтер Canon: 10 главных причин и решения", "i": "🛠️", "c": "remont-i-oshibki"}, {"s": "iz-chego-delayut-toner-dlya-printera", "t": "Состав тонера для принтера: из чего делают и как это работает", "i": "📁", "c": null}, {"s": "iz-chego-sdelany-pampersy-dlya-printera", "t": "Из чего сделаны памперсы для принтера: состав, материалы и замена", "i": "📁", "c": null}, {"s": "iz-chego-delayut-toner-dlya-lazernykh-printerov", "t": "Состав тонера для лазерных принтеров: из чего делают порошок", "i": "📁", "c": null}, {"s": "iz-chego-pechatat-shesterni-na-3d-printere", "t": "Лучший материал для 3D печати шестерен: сравнение PLA, PETG, Nylon и композитов", "i": "📁", "c": null}, {"s": "iz-za-chego-mozhet-polosit-printer", "t": "Почему принтер печатает полосами: 7 причин и способы устранения", "i": "🛠️", "c": "remont-i-oshibki"}, {"s": "iz-chego-pechataet-3-d-printer", "t": "Материалы для 3D печати: обзор филаментов, фотополимеров и порошков", "i": "📁", "c": null}, {"s": "iz-chego-sdelat-absorber-dlya-printera", "t": "Из чего сделать абсорбер для 3D принтера: лучшие материалы и способы", "i": "📁", "c": null}, {"s": "iz-za-chego-printer-pechataet-chernye-listy", "t": "Почему принтер печатает черные листы: причины и ремонт", "i": "🛠️", "c": "remont-i-oshibki"}, {"s": "iz-chego-delaetsya-bumaga-dlya-printera", "t": "Из чего сделана бумага для принтера: состав, производство и выбор", "i": "📁", "c": null}, {"s": "iz-za-chego-plokho-pechataet-printer", "t": "Почему плохо печатает принтер: причины, диагностика и ремонт", "i": "🛠️", "c": "remont-i-oshibki"}, {"s": "iz-chego-delayut-toner-dlya-lazernogo-printera", "t": "Состав тонера для лазерного принтера: из чего делают порошок и жидкий картридж", "i": "📁", "c": null}, {"s": "iz-za-chego-ne-rabotaet-printer", "t": "Почему не работает принтер: 7 главных причин и как их устранить", "i": "📁", "c": null}, {"s": "iz-za-chego-printer-ne-vidit-bumagu", "t": "Принтер не видит бумагу: 7 главных причин и способы устранения", "i": "🛠️", "c": "remont-i-oshibki"}, {"s": "iz-za-chego-printer-pechataet-pustye-listy", "t": "Принтер печатает пустые листы: основные причины и как починить", "i": "🛠️", "c": "remont-i-oshibki"}, {"s": "iz-za-chego-printer-ne-zakhvatyvaet-bumagu-canon", "t": "Принтер Canon не захватывает бумагу: причины, решения и ремонт", "i": "🛠️", "c": "remont-i-oshibki"}, {"s": "iz-chego-delayut-material-dlya-3d-printera", "t": "Из чего делают материал для 3D-принтера: виды, состав и свойства филаментов", "i": "📁", "c": null}, {"s": "iz-chego-sdelan-pampers-dlya-printera", "t": "Из чего сделан памперс для принтера: состав и замена", "i": "🛠️", "c": "remont-i-oshibki"}, {"s": "iz-kakikh-materialov-mozhno-pechatat-na-3d-printere", "t": "Лучшие материалы для 3D печати: виды, свойства и выбор пластика", "i": "📁", "c": null}, {"s": "iz-chego-delayut-printery", "t": "Из чего делают принтеры: материалы корпусов, механизмов и печатающих головок", "i": "📁", "c": null}, {"s": "iz-chego-sdelany-chernila-dlya-strujnogo-printera", "t": "Из чего сделаны чернила для струйного принтера: состав и виды", "i": "📁", "c": null}, {"s": "iz-chego-sdelat-chernila-dlya-printera", "t": "Как сделать чернила для принтера своими руками: состав и инструкция", "i": "📁", "c": null}, {"s": "iz-chego-pechataet-3d-printer", "t": "Материалы для 3D-печати: виды, свойства и выбор филамента", "i": "📁", "c": null}, {"s": "iz-chego-delayut-printery-material", "t": "Из чего делают принтеры: материалы корпуса и узлов", "i": "📁", "c": null}, {"s": "iz-chego-chernila-dlya-lazernogo-printera", "t": "Из чего делают тонер: химический состав чернил лазерного принтера", "i": "📁", "c": null}, {"s": "iz-chego-sostoyat-chernila-v-printere", "t": "Состав чернил для принтера: виды, химия и совместимость", "i": "📁", "c": null}, {"s": "iz-chego-sdelany-kraski-dlya-printera", "t": "Из чего сделаны краски для принтера: состав чернил и картриджей", "i": "📁", "c": null}, {"s": "iz-chego-delayut-toner-dlya-printerov", "t": "Из чего делают тонер для принтеров: состав, свойства и нюансы", "i": "📁", "c": null}, {"s": "iz-chego-sostoyat-chernila-dlya-printera", "t": "Состав чернил для принтера: химия, виды и особенности струйной печати", "i": "📁", "c": null}, {"s": "iz-printera-techet-kraska-chto-delat", "t": "Принтер течет краска: причины, устранение и ремонт своими руками", "i": "🛠️", "c": "remont-i-oshibki"}, {"s": "iz-za-chego-printer-mnet-bumagu", "t": "Почему принтер мнет бумагу: причины, решения и профилактика", "i": "🛠️", "c": "remont-i-oshibki"}, {"s": "iz-za-chego-printer-ne-vidit-kartridzh", "t": "Принтер не видит картридж: 7 причин и способы решения", "i": "📁", "c": null}, {"s": "iz-chego-delayut-absorber-dlya-printera", "t": "Из чего делают абсорбер для принтера: материалы и конструкция", "i": "🛠️", "c": "remont-i-oshibki"}, {"s": "iz-za-chego-dymitsya-printer", "t": "Почему дымит принтер: причины, опасные признаки и действия", "i": "🛠️", "c": "remont-i-oshibki"}, {"s": "iz-za-chego-printer-ne-pechataet-chernym-tsvetom", "t": "Принтер не печатает черным: причины и способы восстановления цвета", "i": "🛠️", "c": "remont-i-oshibki"}, {"s": "iz-chego-pechatat-detali-dlya-3d-printera", "t": "Из чего печатать детали для 3D принтера: выбор материалов и филаментов", "i": "📁", "c": null}, {"s": "iz-za-chego-polosit-lazernyj-printer", "t": "Структурные полосы на принтере: причины и устранение", "i": "🛠️", "c": "remont-i-oshibki"}, {"s": "iz-chego-sostoyat-kartridzhi-dlya-printerov", "t": "Из чего состоят картриджи для принтеров: устройство и компоненты", "i": "📦", "c": "raskhodnye-materialy"}, {"s": "iz-chego-delayut-3d-printery", "t": "Из чего делают 3D-принтеры: Материалы, компоненты и устройство", "i": "📁", "c": null}, {"s": "iz-za-chego-mozhet-printer-ne-pechatat", "t": "Почему принтер не печатает: ТОП-10 причин и способы ремонта", "i": "🛠️", "c": "remont-i-oshibki"}, {"s": "iz-chego-sdelan-toner-dlya-lazernogo-printera", "t": "Состав тонера для лазерного принтера: из чего делают порошок", "i": "📁", "c": null}, {"s": "iz-za-chego-ne-pechataet-printer-hp", "t": "Почему не печатает принтер HP: 7 главных причин и решения", "i": "🛠️", "c": "remont-i-oshibki"}, {"s": "iz-chego-sdelany-chernila-dlya-printera", "t": "Состав чернил для принтера: виды, химия и особенности", "i": "📁", "c": null}, {"s": "iz-kakogo-plastika-pechatat-shesterni-na-3d-printere", "t": "Лучший пластик для 3D-печати шестерен: сравнение материалов и советы", "i": "📁", "c": null}, {"s": "iz-chego-sdelan-absorber-v-printere", "t": "Из чего сделан абсорбер в принтере: материалы, устройство и замена", "i": "🛠️", "c": "remont-i-oshibki"}]