[{"s": "k-kakim-printeram-podkhodit-kartridzh-12a", "t": "Картридж 12А: совместимость с принтерами Canon, HP, Brother", "i": "📦", "c": "raskhodnye-materialy"}, {"s": "k-kakoj-gruppe-osnovnykh-sredstv-otnositsya-printer", "t": "К какой группе ОС относится принтер: классификация 2026 года", "i": "📁", "c": "drugoe"}, {"s": "k-kakomu-klassu-otkhodov-otnosyatsya-kartridzhi-dlya-printerov", "t": "К какому классу отходов относятся картриджи для принтеров в 2026 году", "i": "📁", "c": null}, {"s": "k-chemu-otnesti-kartridzh-dlya-printera", "t": "К чему отнести картридж для принтера: бухгалтерия, налоги, учет 2026", "i": "📁", "c": null}, {"s": "k-kakim-printeram-nedorogie-kartridzhi", "t": "К каким принтерам подходят недорогие картриджи: ТОП-10 моделей 2026", "i": "📁", "c": null}, {"s": "k-kakim-printeram-podkhodit-kartridzh-hp-12a", "t": "Картридж HP 12A: совместимость с принтерами и МФУ (полный список)", "i": "📦", "c": "raskhodnye-materialy"}, {"s": "k-kakoj-amortizatsionnoj-gruppe-otnosyatsya-printer", "t": "Амортизационная группа принтера в 2026 году: как определить правильно", "i": "📁", "c": null}, {"s": "k-kakoj-gruppe-otnositsya-printer", "t": "К какой группе относится принтер: классификация и виды устройств", "i": "📁", "c": null}, {"s": "k-kakomu-klassu-opasnosti-otnosyatsya-kartridzhi-ot-printera", "t": "К какому классу опасности относятся картриджи от принтера в 2026 году?", "i": "📦", "c": "raskhodnye-materialy"}, {"s": "k-kakomu-portu-podklyuchit-printer-cherez-usb", "t": "К какому USB-порту подключить принтер: разъёмы, скорость, совместимость", "i": "📁", "c": null}, {"s": "k-kakomu-printeru-podkhodit-kartridzh-15a", "t": "Картридж 15А: совместимость с принтерами HP, Canon, Pantum", "i": "📁", "c": null}, {"s": "k-kakim-printeram-podkhodit-kartridzh-78a", "t": "Картридж 78А: совместимость с принтерами HP, Canon, Pantum", "i": "📁", "c": null}, {"s": "k-kakomu-vidu-otnositsya-printer", "t": "К какому виду относится принтер: классификация и типы устройств", "i": "📁", "c": null}, {"s": "k-chemu-podklyuchaetsya-printer", "t": "К чему подключается принтер: все способы и нюансы (2026)", "i": "📁", "c": null}, {"s": "k-kakim-portam-kompyutera-mogut-podklyuchatsya-printery", "t": "К каким портам ПК подключают принтеры: полный гайд 2026", "i": "📁", "c": null}, {"s": "k-kakomu-printeru-kartridzh-1710", "t": "Картридж 1710: совместимость с принтерами Canon, HP, Pantum", "i": "📁", "c": null}, {"s": "k-kakim-printeram-podkhodit-kartridzh-hp-650", "t": "Картридж HP 650: совместимость с принтерами и нюансы выбора", "i": "📁", "c": null}, {"s": "k-kakim-printeram-deshevye-kartridzhi", "t": "К каким принтерам дешевые картриджи: топ-10 моделей 2026", "i": "📁", "c": null}, {"s": "k-chemu-snitsya-printer", "t": "К чему снится принтер: 15 толкований снов по сонникам и психологии", "i": "📁", "c": null}, {"s": "k-kakim-printeram-podkhodyat-kartridzhi-2612", "t": "Картриджи 2612: совместимые принтеры и особенности выбора", "i": "📦", "c": "raskhodnye-materialy"}, {"s": "k-chemu-snitsya-printer-pechataet", "t": "К чему снится принтер печатает: 10 толкований снов и технические причины", "i": "📁", "c": null}, {"s": "k-kakim-printeram-podkhodit-kartridzh-cf280x", "t": "Картридж CF280X: совместимость с принтерами Canon, HP и другими", "i": "📁", "c": null}, {"s": "k-kakomu-klassu-otnositsya-printer", "t": "К какому классу относится принтер: классификация и назначение", "i": "📁", "c": null}, {"s": "k-chemu-podklyuchaetsya-printer-k-monitoru-ili-protsessoru", "t": "Куда подключается принтер: к монитору или процессору? Разбор схемы", "i": "📁", "c": null}, {"s": "k-kakim-ustrojstvam-kompyutera-otnositsya-printer", "t": "Принтер — это периферийное устройство или нет? Разбираемся в классификации", "i": "📁", "c": null}, {"s": "k-chemu-otnosyatsya-printer-monitor-klaviatura", "t": "Принтер, монитор, клавиатура — к какой категории устройств они относятся?", "i": "📁", "c": null}, {"s": "k-kakoj-kategorii-otnosyatsya-printery", "t": "К какой категории относятся принтеры: классификация и виды", "i": "📁", "c": null}, {"s": "k-kakim-printeram-podkhodyat-kartridzhi-12a", "t": "К каким принтерам подходят картриджи 12А: полный список совместимых моделей", "i": "📦", "c": "raskhodnye-materialy"}, {"s": "k-kakomu-printeru-kartridzh-703", "t": "Картридж 703: совместимость, принтеры HP и замена чернил", "i": "📁", "c": null}, {"s": "k-kakoj-amortizatsionnoj-gruppe-otnositsya-printer", "t": "К какой амортизационной группе относится принтер: таблица и правила", "i": "📁", "c": null}, {"s": "k-kakim-printeram-podkhodyat-kartridzhi-36a", "t": "Совместимость картриджей 36A: какие принтеры и МФУ поддерживают", "i": "📁", "c": null}, {"s": "k-kakomu-portu-podklyuchaetsya-printer", "t": "К какому порту подключается принтер: Выбор и настройка", "i": "📁", "c": null}, {"s": "k-kakomu-klassu-opasnosti-otnositsya-printer", "t": "К какому классу опасности относится принтер: отходы и утилизация", "i": "📁", "c": null}, {"s": "k-kakomu-oborudovaniyu-otnosyatsya-printery", "t": "К какому оборудованию относятся принтеры: классификация и виды", "i": "📁", "c": null}, {"s": "k-kakim-printeram-podkhodit-kartridzh-725-kenon", "t": "Совместимость картриджа Canon 725: список принтеров, замена и аналоги", "i": "📁", "c": null}, {"s": "k-kakim-printeram-podkhodit-kartridzh-ce278a", "t": "Совместимость картриджа CE278A: модели принтеров HP и замены", "i": "📁", "c": null}, {"s": "k-kakim-printeram-podkhodit-kartridzh-canon-725", "t": "Совместимость картриджа Canon 725: список принтеров и МФУ", "i": "📁", "c": null}, {"s": "k-kakoj-gruppe-otnesti-printer", "t": "К какой группе отнести принтер: классификация для бизнеса и склада", "i": "📁", "c": null}, {"s": "k-kakim-printeram-hp-podkhodit-kartridzh-121", "t": "К каким принтерам HP подходит картридж 121: полный список моделей", "i": "📁", "c": null}, {"s": "k-kakomu-routeru-mozhno-podklyuchit-printer", "t": "Как подключить принтер к роутеру: выбор модели и настройка Wi-Fi печати", "i": "📁", "c": null}, {"s": "k-kakim-printeram-podkhodit-kartridzh-hp-122", "t": "Совместимые принтеры HP для картриджа 122: полный список моделей", "i": "📦", "c": "raskhodnye-materialy"}, {"s": "k-kakomu-tipu-ustrojstv-otnositsya-printer", "t": "К какому типу устройств относится принтер: классификация и виды", "i": "📁", "c": null}, {"s": "k-kakim-ustrojstvam-otnositsya-printer", "t": "К каким устройствам относится принтер: классификация и виды", "i": "📁", "c": null}, {"s": "k-kakomu-printeru-podkhodit-kartridzh-85a", "t": "Картридж 85А: совместимые принтеры HP, совместимость и выбор", "i": "📁", "c": null}, {"s": "k-kakomu-printeru-podkhodit-kartridzh-se278a", "t": "Принтеры для картриджа CE278A: полный список совместимых моделей HP", "i": "📁", "c": null}, {"s": "k-kakomu-portu-dolzhen-byt-podklyuchen-printer", "t": "Какому порту должен быть подключен принтер: сетевые настройки и протоколы", "i": "📁", "c": null}, {"s": "k-kakomu-printeru-kartridzh-436a", "t": "К какому принтеру подходит картридж HP 436A: полная совместимость", "i": "📦", "c": "raskhodnye-materialy"}, {"s": "k-chemu-otnositsya-printer-v-informatike", "t": "Классификация принтера в информатике: устройство и роль в сети", "i": "📁", "c": null}, {"s": "k-kakomu-printeru-samye-deshevye-kartridzhi", "t": "Какому принтеру самые дешевые картриджи: рейтинг экономных моделей", "i": "📁", "c": null}, {"s": "k-kakomu-portu-podklyuchat-printer", "t": "К какому порту подключать принтер: USB, Сеть или Wi-Fi", "i": "📁", "c": null}, {"s": "k-chemu-otnositsya-printer-skaner", "t": "К какой категории относится принтер-сканер: классификация и назначение", "i": "📁", "c": null}, {"s": "k-kakoj-informatsii-otnositsya-printer", "t": "К какой информации относится принтер: классификация данных и носителей", "i": "📁", "c": null}, {"s": "k-kakomu-printeru-podkhodit-kartridzh-712", "t": "К какому принтеру подходит картридж 712: полная совместимость Canon", "i": "📦", "c": "raskhodnye-materialy"}, {"s": "k-chemu-podklyuchaetsya-mini-printer", "t": "К чему подключается мини-принтер: интерфейсы, кабели и настройка", "i": "📁", "c": null}, {"s": "k-chemu-otnosyatsya-kartridzhi-dlya-printerov", "t": "К чему относятся картриджи для принтеров: виды, совместимость и выбор", "i": "📦", "c": "raskhodnye-materialy"}, {"s": "k-kakim-printeram-podkhodit-kartridzh-hp-123", "t": "Какие принтеры используют картридж HP 123: полный список моделей", "i": "📁", "c": null}, {"s": "k-chemu-otnosyatsya-printery", "t": "К какому классу относятся принтеры: классификация и назначение", "i": "📁", "c": null}, {"s": "k-kakim-printeram-podkhodit-kartridzh-canon-ep-22", "t": "Совместимость картриджа Canon EP-22: список принтеров и модели", "i": "📁", "c": null}, {"s": "k-kakomu-portu-mozhno-podklyuchit-printer", "t": "К какому порту подключить принтер: USB, LAN, Wi-Fi и LPT", "i": "📁", "c": null}, {"s": "k-kakomu-printeru-podkhodit-kartridzh-ep-22", "t": "Совместимость картриджа EP-22: список принтеров Canon и инструкция", "i": "📦", "c": "raskhodnye-materialy"}, {"s": "k-kakomu-printeru-podkhodit-kartridzh-q2612a", "t": "Совместимость картриджа Q2612A: список принтеров HP и аналоги", "i": "📦", "c": "raskhodnye-materialy"}, {"s": "k-kakim-printeram-podkhodit-kartridzh-canon-712", "t": "Совместимость картриджа Canon 712: список принтеров и МФУ", "i": "📁", "c": null}, {"s": "k-kakim-printeram-podkhodit-kartridzh-ep-22", "t": "Совместимость картриджа EP-22: модели принтеров Canon и заправка", "i": "📦", "c": "raskhodnye-materialy"}, {"s": "k-kakomu-klassu-opasnosti-otnosyatsya-printery", "t": "К какому классу опасности относятся принтеры: разбор отходов и утилизации", "i": "📁", "c": null}, {"s": "k-kakomu-portu-podklyuchit-printer-hp", "t": "К какому порту подключить принтер HP: USB, сеть и Wi-Fi", "i": "📁", "c": null}, {"s": "k-chemu-podklyuchaetsya-setevoj-printer", "t": "К чему подключается сетевой принтер: методы настройки и варианты", "i": "📁", "c": null}, {"s": "k-kakomu-okof-otnesti-printer", "t": "К какому ОКОФ отнести принтер: актуальные коды и амортизация", "i": "📁", "c": null}, {"s": "k-kakim-printeram-podkhodit-kartridzh-92a", "t": "Совместимость картриджа 92А: к каким принтерам подходит", "i": "📁", "c": null}, {"s": "k-kakomu-tipu-otnositsya-printer", "t": "К какому типу относится принтер: классификация и выбор технологии", "i": "📁", "c": null}, {"s": "k-kakim-printeram-podkhodit-kartridzh-hp-652", "t": "Совместимость картриджа HP 652: список принтеров HP DeskJet", "i": "📦", "c": "raskhodnye-materialy"}, {"s": "k-kakim-ustrojstvam-kompyutera-otnosyatsya-dannye-elementy-printer", "t": "К каким устройствам относится принтер: классификация и типы периферии", "i": "📁", "c": null}, {"s": "k-kakim-printeram-podkhodit-kartridzh-85-a", "t": "К каким принтерам подходит картридж 85A: полный список моделей HP", "i": "📁", "c": null}, {"s": "k-kakim-printeram-podkhodit-kartridzh-cb435a", "t": "Совместимые принтеры для картриджа CB435A: полный список моделей HP", "i": "📁", "c": null}]