[{"s": "lide-110-canon-kak-razobrat", "t": "Canon LiDE 110: как разобрать сканер без повреждений — пошагово", "i": "📁", "c": null}, {"s": "list-dlya-printera-kakoj-format", "t": "Формат листа для принтера: какой выбрать и как не ошибиться", "i": "📁", "c": null}, {"s": "linux-kak-nastroit-setevoj-printer", "t": "Как настроить сетевой принтер в Linux: пошаговая инструкция", "i": "📁", "c": null}, {"s": "linux-mint-kak-dobavit-printer", "t": "Как добавить принтер в Linux Mint: Пошаговая инструкция", "i": "📁", "c": null}, {"s": "live-view-canon-kak-vklyuchit-rezhim", "t": "Как включить режим Live View на камерах Canon: Полная инструкция", "i": "📁", "c": "drugoe"}, {"s": "linux-kak-dobavit-printer", "t": "Как добавить принтер в Linux: пошаговая инструкция настройки CUPS", "i": "📁", "c": null}, {"s": "list-zastryal-v-printere-kak-dostat-pantum", "t": "Как достать застрявший лист из принтера Pantum: пошаговая инструкция", "i": "📁", "c": null}, {"s": "live-view-canon-kak-vklyuchit", "t": "Как включить Live View на Canon: Полная инструкция по режиму Live View", "i": "📁", "c": null}, {"s": "listy-dlya-printera-kak", "t": "Как правильно выбрать и загрузить листы для принтера: типы, плотность и ошибки", "i": "📁", "c": null}, {"s": "live-view-canon-chto-eto", "t": "Live View Canon: что это и как использовать режим на камере", "i": "📁", "c": null}, {"s": "linux-mint-kak-podklyuchit-printer", "t": "Как подключить принтер в Linux Mint: Полное руководство", "i": "📁", "c": null}, {"s": "linux-mint-kak-ustanovit-printer", "t": "Как установить принтер в Linux Mint: полное руководство", "i": "📁", "c": null}]